c8_source_oracle/__init__.py
c8_source_oracle/db.py
c8_source_oracle/sync_strategies/__init__.py
c8_source_oracle/sync_strategies/common.py
c8_source_oracle/sync_strategies/full_table.py
c8_source_oracle/sync_strategies/incremental.py
c8_source_oracle/sync_strategies/log_miner.py
c8_source_oracle-0.0.7.dist-info/entry_points.txt
c8_source_oracle-0.0.7.dist-info/LICENSE
c8_source_oracle-0.0.7.dist-info/WHEEL
c8_source_oracle-0.0.7.dist-info/METADATA
c8_source_oracle-0.0.7.dist-info/RECORD
