Metadata-Version: 2.1
Name: c8-source-oracle
Version: 0.0.7
Summary: Pipelinewise tap for reading from oracle databases. This includes support for PDBs.
Home-page: https://www.macrometa.com/
License: Apache-2.0
Keywords: ELT,Connectors,Workflows,Macrometa,Oracle,Tap
Author: Macrometa
Author-email: info@macrometa.com
Requires-Python: >=3.7
Classifier: License :: OSI Approved :: Apache Software License
Classifier: Operating System :: OS Independent
Classifier: Programming Language :: Python :: 3
Classifier: Programming Language :: Python :: 3.7
Classifier: Programming Language :: Python :: 3.8
Classifier: Programming Language :: Python :: 3.9
Classifier: Programming Language :: Python :: 3.10
Classifier: Programming Language :: Python :: 3
Classifier: Programming Language :: Python :: 3.7
Requires-Dist: c8connector (>=0,<1)
Requires-Dist: cx-oracle (>=8.3.0,<9.0.0)
Requires-Dist: pipelinewise-singer-python (==1.2.0)
Requires-Dist: strict-rfc3339 (>=0.7,<0.8)
Project-URL: Bug Tracker, https://github.com/Macrometacorp/c8-source-oracle/issues
